project_structure_extractor/__init__.py
project_structure_extractor/cli.py
project_structure_extractor/extractor.py
project_structure_extractor-0.1.3.dist-info/LICENSE
project_structure_extractor-0.1.3.dist-info/METADATA
project_structure_extractor-0.1.3.dist-info/WHEEL
project_structure_extractor-0.1.3.dist-info/entry_points.txt
project_structure_extractor-0.1.3.dist-info/top_level.txt
project_structure_extractor-0.1.3.dist-info/RECORD
