Metadata-Version: 2.1
Name: project-structure-extractor
Version: 0.1.3
Summary: CLI tool to extract the structure of a project into a .txt file.
Home-page: https://github.com/RealWorga/project-structure-extractor
Author: Hamed Haghjo
Author-email: hamedhaghjo@hotmail.com
Classifier: Programming Language :: Python :: 3
Classifier: License :: OSI Approved :: MIT License
Classifier: Operating System :: OS Independent
License-File: LICENSE
Requires-Dist: Click
